format_tree/__init__.py
format_tree/format_tree.py
format_tree-0.2.3.dist-info/licenses/LICENSE
format_tree-0.2.3.dist-info/METADATA
format_tree-0.2.3.dist-info/WHEEL
format_tree-0.2.3.dist-info/top_level.txt
format_tree-0.2.3.dist-info/RECORD
