Metadata-Version: 2.4
Name: format_tree
Version: 0.2.3
Summary: Advanced formatting, analysis, and visualization utilities for scikit-learn decision trees.
Home-page: https://github.com/k-explore/format_tree
Author: Kathy G
Author-email: kguo715@gmail.com
License: MIT
Project-URL: Documentation, https://github.com/k-explore/format_tree#readme
Project-URL: Source, https://github.com/k-explore/format_tree
Project-URL: Tracker, https://github.com/k-explore/format_tree/issues
Project-URL: PyPI, https://pypi.org/project/format_tree/
Keywords: decision tree,visualization,sklearn,matplotlib,pandas,analysis,data science,machine learning
Classifier: Programming Language :: Python :: 3
Classifier: License :: OSI Approved :: MIT License
Classifier: Operating System :: OS Independent
Classifier: Intended Audience :: Developers
Classifier: Intended Audience :: Science/Research
Classifier: Topic :: Scientific/Engineering :: Visualization
Classifier: Topic :: Scientific/Engineering :: Information Analysis
Classifier: Framework :: Matplotlib
Requires-Python: >=3.7
License-File: LICENSE
Requires-Dist: numpy>=1.18
Requires-Dist: matplotlib>=3.2
Requires-Dist: scikit-learn>=0.24
Requires-Dist: pandas>=1.0
Dynamic: author
Dynamic: author-email
Dynamic: classifier
Dynamic: description
Dynamic: description-content-type
Dynamic: home-page
Dynamic: keywords
Dynamic: license
Dynamic: license-file
Dynamic: project-url
Dynamic: requires-dist
Dynamic: requires-python
Dynamic: summary
